{"v":"5.6.8","fr":30,"ip":0,"op":60,"w":600,"h":600,"nm":"circle revolving","ddd":0,"assets":[],"layers":[{"ddd":0,"ind":1,"ty":4,"nm":"White color 2","sr":1,"ks":{"o":{"a":0,"k":100,"ix":11},"r":{"a":0,"k":0,"ix":10},"p":{"a":1,"k":[{"i":{"x":0.466,"y":1},"o":{"x":0.542,"y":0},"t":0,"s":[200,300,0],"to":[25.808,0,0],"ti":[0,0,0]},{"i":{"x":0.475,"y":1},"o":{"x":0.534,"y":0},"t":30,"s":[400,300,0],"to":[0,0,0],"ti":[25.808,0,0]},{"t":60,"s":[200,300,0]}],"ix":2},"a":{"a":0,"k":[0,0,0],"ix":1},"s":{"a":1,"k":[{"i":{"x":[0.771,0.771,0.771],"y":[1,1,1]},"o":{"x":[0.537,0.537,0.537],"y":[0,0,0]},"t":0,"s":[100,100,100]},{"i":{"x":[0.462,0.462,0.462],"y":[1,1,1]},"o":{"x":[0.233,0.233,0.233],"y":[0,0,0]},"t":15,"s":[80,80,100]},{"i":{"x":[0.767,0.767,0.767],"y":[1,1,1]},"o":{"x":[0.529,0.529,0.529],"y":[0,0,0]},"t":30,"s":[100,100,100]},{"i":{"x":[0.47,0.47,0.47],"y":[1,1,1]},"o":{"x":[0.237,0.237,0.237],"y":[0,0,0]},"t":45,"s":[150,150,100]},{"t":60,"s":[100,100,100]}],"ix":6}},"ao":0,"shapes":[{"ty":"gr","it":[{"d":1,"ty":"el","s":{"a":0,"k":[75,75],"ix":2},"p":{"a":0,"k":[0,0],"ix":3},"nm":"Ellipse Path 1","mn":"ADBE Vector Shape - Ellipse","hd":false},{"ty":"fl","c":{"a":0,"k":[1,0.4196078431372549,0.4196078431372549,1],"ix":4},"o":{"a":0,"k":100,"ix":5},"r":1,"bm":0,"nm":"Fill 1","mn":"ADBE Vector Graphic - Fill","hd":false},{"ty":"tr","p":{"a":0,"k":[0,0],"ix":2},"a":{"a":0,"k":[0,0],"ix":1},"s":{"a":0,"k":[100,100],"ix":3},"r":{"a":0,"k":0,"ix":6},"o":{"a":0,"k":100,"ix":7},"sk":{"a":0,"k":0,"ix":4},"sa":{"a":0,"k":0,"ix":5},"nm":"Transform"}],"nm":"Ellipse 1","np":3,"cix":2,"bm":0,"ix":1,"mn":"ADBE Vector Group","hd":false}],"ip":30,"op":60,"st":0,"bm":0},{"ddd":0,"ind":2,"ty":4,"nm":"Dark Color 2","sr":1,"ks":{"o":{"a":0,"k":100,"ix":11},"r":{"a":0,"k":0,"ix":10},"p":{"a":1,"k":[{"i":{"x":0.466,"y":1},"o":{"x":0.542,"y":0},"t":0,"s":[400,300,0],"to":[0,0,0],"ti":[0,0,0]},{"i":{"x":0.475,"y":1},"o":{"x":0.534,"y":0},"t":30,"s":[200,300,0],"to":[0,0,0],"ti":[0,0,0]},{"t":60,"s":[400,300,0]}],"ix":2},"a":{"a":0,"k":[0,0,0],"ix":1},"s":{"a":1,"k":[{"i":{"x":[0.771,0.771,0.771],"y":[1,1,1]},"o":{"x":[0.537,0.537,0.537],"y":[0,0,0]},"t":0,"s":[100,100,100]},{"i":{"x":[0.462,0.462,0.462],"y":[1,1,1]},"o":{"x":[0.233,0.233,0.233],"y":[0,0,0]},"t":15,"s":[120,120,100]},{"i":{"x":[0.767,0.767,0.767],"y":[1,1,1]},"o":{"x":[0.529,0.529,0.529],"y":[0,0,0]},"t":30,"s":[100,100,100]},{"i":{"x":[0.47,0.47,0.47],"y":[1,1,1]},"o":{"x":[0.237,0.237,0.237],"y":[0,0,0]},"t":45,"s":[70,70,100]},{"t":60,"s":[100,100,100]}],"ix":6}},"ao":0,"shapes":[{"ty":"gr","it":[{"d":1,"ty":"el","s":{"a":0,"k":[75,75],"ix":2},"p":{"a":0,"k":[0,0],"ix":3},"nm":"Ellipse Path 1","mn":"ADBE Vector Shape - Ellipse","hd":false},{"ty":"fl","c":{"a":0,"k":[0.5176470588235295,0.3686274509803922,0.9686274509803922,1],"ix":4},"o":{"a":0,"k":100,"ix":5},"r":1,"bm":0,"nm":"Fill 1","mn":"ADBE Vector Graphic - Fill","hd":false},{"ty":"tr","p":{"a":0,"k":[0,0],"ix":2},"a":{"a":0,"k":[0,0],"ix":1},"s":{"a":0,"k":[100,100],"ix":3},"r":{"a":0,"k":0,"ix":6},"o":{"a":0,"k":100,"ix":7},"sk":{"a":0,"k":0,"ix":4},"sa":{"a":0,"k":0,"ix":5},"nm":"Transform"}],"nm":"Ellipse 1","np":3,"cix":2,"bm":0,"ix":1,"mn":"ADBE Vector Group","hd":false}],"ip":30,"op":60,"st":0,"bm":0},{"ddd":0,"ind":3,"ty":4,"nm":"Dark Color","sr":1,"ks":{"o":{"a":0,"k":100,"ix":11},"r":{"a":0,"k":0,"ix":10},"p":{"a":1,"k":[{"i":{"x":0.466,"y":1},"o":{"x":0.542,"y":0},"t":0,"s":[400,300,0],"to":[0,0,0],"ti":[0,0,0]},{"i":{"x":0.475,"y":1},"o":{"x":0.534,"y":0},"t":30,"s":[200,300,0],"to":[0,0,0],"ti":[0,0,0]},{"t":60,"s":[400,300,0]}],"ix":2},"a":{"a":0,"k":[0,0,0],"ix":1},"s":{"a":1,"k":[{"i":{"x":[0.771,0.771,0.771],"y":[1,1,1]},"o":{"x":[0.537,0.537,0.537],"y":[0,0,0]},"t":0,"s":[100,100,100]},{"i":{"x":[0.462,0.462,0.462],"y":[1,1,1]},"o":{"x":[0.233,0.233,0.233],"y":[0,0,0]},"t":15,"s":[150,150,100]},{"i":{"x":[0.767,0.767,0.767],"y":[1,1,1]},"o":{"x":[0.529,0.529,0.529],"y":[0,0,0]},"t":30,"s":[100,100,100]},{"i":{"x":[0.47,0.47,0.47],"y":[1,1,1]},"o":{"x":[0.237,0.237,0.237],"y":[0,0,0]},"t":45,"s":[150,150,100]},{"t":60,"s":[100,100,100]}],"ix":6}},"ao":0,"shapes":[{"ty":"gr","it":[{"d":1,"ty":"el","s":{"a":0,"k":[75,75],"ix":2},"p":{"a":0,"k":[0,0],"ix":3},"nm":"Ellipse Path 1","mn":"ADBE Vector Shape - Ellipse","hd":false},{"ty":"fl","c":{"a":0,"k":[0.5176470588235295,0.3686274509803922,0.9686274509803922,1],"ix":4},"o":{"a":0,"k":100,"ix":5},"r":1,"bm":0,"nm":"Fill 1","mn":"ADBE Vector Graphic - Fill","hd":false},{"ty":"tr","p":{"a":0,"k":[0,0],"ix":2},"a":{"a":0,"k":[0,0],"ix":1},"s":{"a":0,"k":[100,100],"ix":3},"r":{"a":0,"k":0,"ix":6},"o":{"a":0,"k":100,"ix":7},"sk":{"a":0,"k":0,"ix":4},"sa":{"a":0,"k":0,"ix":5},"nm":"Transform"}],"nm":"Ellipse 1","np":3,"cix":2,"bm":0,"ix":1,"mn":"ADBE Vector Group","hd":false}],"ip":0,"op":30,"st":0,"bm":0},{"ddd":0,"ind":4,"ty":4,"nm":"White color","sr":1,"ks":{"o":{"a":0,"k":100,"ix":11},"r":{"a":0,"k":0,"ix":10},"p":{"a":1,"k":[{"i":{"x":0.466,"y":1},"o":{"x":0.542,"y":0},"t":0,"s":[200,300,0],"to":[25.808,0,0],"ti":[0,0,0]},{"i":{"x":0.475,"y":1},"o":{"x":0.534,"y":0},"t":30,"s":[400,300,0],"to":[0,0,0],"ti":[25.808,0,0]},{"t":60,"s":[200,300,0]}],"ix":2},"a":{"a":0,"k":[0,0,0],"ix":1},"s":{"a":1,"k":[{"i":{"x":[0.771,0.771,0.771],"y":[1,1,1]},"o":{"x":[0.537,0.537,0.537],"y":[0,0,0]},"t":0,"s":[100,100,100]},{"i":{"x":[0.462,0.462,0.462],"y":[1,1,1]},"o":{"x":[0.233,0.233,0.233],"y":[0,0,0]},"t":15,"s":[70,70,100]},{"i":{"x":[0.767,0.767,0.767],"y":[1,1,1]},"o":{"x":[0.529,0.529,0.529],"y":[0,0,0]},"t":30,"s":[100,100,100]},{"i":{"x":[0.47,0.47,0.47],"y":[1,1,1]},"o":{"x":[0.237,0.237,0.237],"y":[0,0,0]},"t":45,"s":[120,120,100]},{"t":60,"s":[100,100,100]}],"ix":6}},"ao":0,"shapes":[{"ty":"gr","it":[{"d":1,"ty":"el","s":{"a":0,"k":[75,75],"ix":2},"p":{"a":0,"k":[0,0],"ix":3},"nm":"Ellipse Path 1","mn":"ADBE Vector Shape - Ellipse","hd":false},{"ty":"fl","c":{"a":0,"k":[1,0.4196078431372549,0.4196078431372549,1],"ix":4},"o":{"a":0,"k":100,"ix":5},"r":1,"bm":0,"nm":"Fill 1","mn":"ADBE Vector Graphic - Fill","hd":false},{"ty":"tr","p":{"a":0,"k":[0,0],"ix":2},"a":{"a":0,"k":[0,0],"ix":1},"s":{"a":0,"k":[100,100],"ix":3},"r":{"a":0,"k":0,"ix":6},"o":{"a":0,"k":100,"ix":7},"sk":{"a":0,"k":0,"ix":4},"sa":{"a":0,"k":0,"ix":5},"nm":"Transform"}],"nm":"Ellipse 1","np":3,"cix":2,"bm":0,"ix":1,"mn":"ADBE Vector Group","hd":false}],"ip":0,"op":30,"st":0,"bm":0}],"markers":[]}